nh_lib/__init__.py
nh_lib/script_librerias.py
script_librerias-0.1.0.dist-info/licenses/LICENSE
script_librerias-0.1.0.dist-info/METADATA
script_librerias-0.1.0.dist-info/WHEEL
script_librerias-0.1.0.dist-info/top_level.txt
script_librerias-0.1.0.dist-info/RECORD
