Metadata-Version: 2.4
Name: script_librerias
Version: 0.1.0
Summary: Repository containing the Minor BI team's Python library, featuring features we use every day.
Home-page: https://https://github.com/nhbigithub/Python_Library
Author: BI Minor Hotels
Author-email: b.intelligence@minor-hotels.com
Classifier: Programming Language :: Python :: 3
Classifier: License :: OSI Approved :: MIT License
Classifier: Operating System :: OS Independent
Requires-Python: >=3.7
License-File: LICENSE
Dynamic: author
Dynamic: author-email
Dynamic: classifier
Dynamic: description
Dynamic: description-content-type
Dynamic: home-page
Dynamic: license-file
Dynamic: requires-python
Dynamic: summary
